monzo/__init__.py
monzo/auth.py
monzo/const.py
monzo/errors.py
monzo/monzo.py
monzo/utils.py
monzo-test/__init__.py
monzo-test/auth.py
monzo-test/errors.py
monzo-test/monzo.py
monzotomtest-0.6.3.dist-info/METADATA
monzotomtest-0.6.3.dist-info/RECORD
monzotomtest-0.6.3.dist-info/WHEEL
monzotomtest-0.6.3.dist-info/top_level.txt
