Metadata-Version: 2.1
Name: monzotomtest
Version: 0.6.3
Summary: A python SDK for interacting with the Monzo API.
Home-page: https://github.com/muyiwaolu/monzo-python
Author: Muyiwa Olu-Ogunleye
Author-email: m.oluogunleye94@gmail.com
License: MIT
Platform: UNKNOWN
Requires-Dist: requests
Requires-Dist: requests-oauthlib
Requires-Dist: python-dotenv
